{
	"$schema": "http://schema.management.azure.com/schemas/2015-01-01/deploymentTemplate.json#",
	"contentVersion": "1.0.0.0",
	"parameters": {
		"factoryName": {
			"type": "string",
			"metadata": "データ ファクトリ名",
			"defaultValue": "ADF-taizawa002"
		}
	},
	"variables": {
		"factoryId": "[concat('Microsoft.DataFactory/factories/', parameters('factoryName'))]"
	},
	"resources": [
		{
			"name": "[concat(parameters('factoryName'), '/CopyPipeline_64o')]",
			"type": "Microsoft.DataFactory/factories/pipelines",
			"apiVersion": "2018-06-01",
			"properties": {
				"activities": [
					{
						"name": "Copy_64o",
						"type": "Copy",
						"dependsOn": [],
						"policy": {
							"timeout": "7.00:00:00",
							"retry": 0,
							"retryIntervalInSeconds": 30,
							"secureOutput": false,
							"secureInput": false
						},
						"userProperties": [
							{
								"name": "Source",
								"value": "input//"
							},
							{
								"name": "Destination",
								"value": "output//"
							}
						],
						"typeProperties": {
							"source": {
								"type": "DelimitedTextSource",
								"storeSettings": {
									"type": "AzureBlobStorageReadSettings",
									"recursive": true,
									"wildcardFileName": "*",
									"enablePartitionDiscovery": false
								},
								"formatSettings": {
									"type": "DelimitedTextReadSettings",
									"skipLineCount": 0
								}
							},
							"sink": {
								"type": "DelimitedTextSink",
								"storeSettings": {
									"type": "AzureBlobStorageWriteSettings"
								},
								"formatSettings": {
									"type": "DelimitedTextWriteSettings",
									"quoteAllText": true,
									"fileExtension": ".txt"
								}
							},
							"enableStaging": false,
							"validateDataConsistency": false
						},
						"inputs": [
							{
								"referenceName": "SourceDataset_64o",
								"type": "DatasetReference",
								"parameters": {}
							}
						],
						"outputs": [
							{
								"referenceName": "DestinationDataset_64o",
								"type": "DatasetReference",
								"parameters": {}
							}
						]
					}
				],
				"policy": {
					"elapsedTimeMetric": {}
				},
				"folder": {
					"name": "ADFTest"
				},
				"annotations": [],
				"lastPublishTime": "2022-07-26T05:43:15Z"
			},
			"dependsOn": []
		},
		{
			"name": "[concat(parameters('factoryName'), '/CopyPipeline_ja0')]",
			"type": "Microsoft.DataFactory/factories/pipelines",
			"apiVersion": "2018-06-01",
			"properties": {
				"activities": [
					{
						"name": "Copy_ja0",
						"type": "Copy",
						"dependsOn": [],
						"policy": {
							"timeout": "7.00:00:00",
							"retry": 0,
							"retryIntervalInSeconds": 30,
							"secureOutput": false,
							"secureInput": false
						},
						"userProperties": [
							{
								"name": "Source",
								"value": "excelinput//"
							},
							{
								"name": "Destination",
								"value": "exceloutput//"
							}
						],
						"typeProperties": {
							"source": {
								"type": "BinarySource",
								"storeSettings": {
									"type": "AzureBlobStorageReadSettings",
									"recursive": false,
									"wildcardFileName": "*",
									"deleteFilesAfterCompletion": false
								},
								"formatSettings": {
									"type": "BinaryReadSettings"
								}
							},
							"sink": {
								"type": "BinarySink",
								"storeSettings": {
									"type": "AzureBlobFSWriteSettings"
								}
							},
							"enableStaging": false,
							"enableSkipIncompatibleRow": false,
							"skipErrorFile": {
								"fileMissing": true
							},
							"validateDataConsistency": false
						},
						"inputs": [
							{
								"referenceName": "SourceDataset_ja0",
								"type": "DatasetReference",
								"parameters": {}
							}
						],
						"outputs": [
							{
								"referenceName": "DestinationDataset_ja0",
								"type": "DatasetReference",
								"parameters": {}
							}
						]
					}
				],
				"policy": {
					"elapsedTimeMetric": {}
				},
				"folder": {
					"name": "ADFTest"
				},
				"annotations": [],
				"lastPublishTime": "2022-07-26T05:43:15Z"
			},
			"dependsOn": []
		},
		{
			"name": "[concat(parameters('factoryName'), '/CopyPipeline_vk4')]",
			"type": "Microsoft.DataFactory/factories/pipelines",
			"apiVersion": "2018-06-01",
			"properties": {
				"activities": [
					{
						"name": "Copy_vk4",
						"type": "Copy",
						"dependsOn": [],
						"policy": {
							"timeout": "7.00:00:00",
							"retry": 0,
							"retryIntervalInSeconds": 30,
							"secureOutput": false,
							"secureInput": false
						},
						"userProperties": [
							{
								"name": "Source",
								"value": "input//"
							},
							{
								"name": "Destination",
								"value": "output//"
							}
						],
						"typeProperties": {
							"source": {
								"type": "BinarySource",
								"storeSettings": {
									"type": "AzureBlobStorageReadSettings",
									"recursive": true,
									"wildcardFileName": "*"
								},
								"formatSettings": {
									"type": "BinaryReadSettings"
								}
							},
							"sink": {
								"type": "BinarySink",
								"storeSettings": {
									"type": "AzureBlobStorageWriteSettings"
								}
							},
							"enableStaging": false,
							"enableSkipIncompatibleRow": false,
							"skipErrorFile": {
								"fileMissing": true
							},
							"validateDataConsistency": false
						},
						"inputs": [
							{
								"referenceName": "SourceDataset_vk4",
								"type": "DatasetReference",
								"parameters": {}
							}
						],
						"outputs": [
							{
								"referenceName": "DestinationDataset_vk4",
								"type": "DatasetReference",
								"parameters": {}
							}
						]
					}
				],
				"policy": {
					"elapsedTimeMetric": {}
				},
				"folder": {
					"name": "ADFTest"
				},
				"annotations": [],
				"lastPublishTime": "2022-07-26T05:43:15Z"
			},
			"dependsOn": []
		},
		{
			"name": "[concat(parameters('factoryName'), '/JSON_Convert')]",
			"type": "Microsoft.DataFactory/factories/pipelines",
			"apiVersion": "2018-06-01",
			"properties": {
				"activities": [
					{
						"name": "Copy data1",
						"type": "Copy",
						"dependsOn": [],
						"policy": {
							"timeout": "0.12:00:00",
							"retry": 0,
							"retryIntervalInSeconds": 30,
							"secureOutput": false,
							"secureInput": false
						},
						"userProperties": [],
						"typeProperties": {
							"source": {
								"type": "DelimitedTextSource",
								"storeSettings": {
									"type": "AzureBlobStorageReadSettings",
									"recursive": true,
									"wildcardFileName": "*.json",
									"enablePartitionDiscovery": false
								},
								"formatSettings": {
									"type": "DelimitedTextReadSettings"
								}
							},
							"sink": {
								"type": "JsonSink",
								"storeSettings": {
									"type": "AzureBlobStorageWriteSettings"
								},
								"formatSettings": {
									"type": "JsonWriteSettings"
								}
							},
							"enableStaging": false,
							"translator": {
								"type": "TabularTranslator",
								"mappings": [
									{
										"source": {
											"name": "exchange_criteria",
											"type": "String"
										},
										"sink": {
											"path": "exchange_criteria"
										}
									},
									{
										"source": {
											"name": "redeem_criteria",
											"type": "String"
										},
										"sink": {
											"path": "redeem_criteria"
										}
									}
								]
							}
						},
						"inputs": [
							{
								"referenceName": "DelimitedText_with_JSON",
								"type": "DatasetReference",
								"parameters": {}
							}
						],
						"outputs": [
							{
								"referenceName": "Json1",
								"type": "DatasetReference",
								"parameters": {}
							}
						]
					}
				],
				"policy": {
					"elapsedTimeMetric": {}
				},
				"folder": {
					"name": "ADFTest"
				},
				"annotations": []
			},
			"dependsOn": []
		},
		{
			"name": "[concat(parameters('factoryName'), '/RenameTest')]",
			"type": "Microsoft.DataFactory/factories/pipelines",
			"apiVersion": "2018-06-01",
			"properties": {
				"activities": [
					{
						"name": "Copy data1",
						"type": "Copy",
						"dependsOn": [],
						"policy": {
							"timeout": "7.00:00:00",
							"retry": 0,
							"retryIntervalInSeconds": 30,
							"secureOutput": false,
							"secureInput": false
						},
						"userProperties": [],
						"typeProperties": {
							"source": {
								"type": "BinarySource",
								"storeSettings": {
									"type": "AzureBlobStorageReadSettings",
									"recursive": true,
									"wildcardFileName": {
										"value": "@pipeline().parameters.p2",
										"type": "Expression"
									},
									"deleteFilesAfterCompletion": false
								},
								"formatSettings": {
									"type": "BinaryReadSettings"
								}
							},
							"sink": {
								"type": "BinarySink",
								"storeSettings": {
									"type": "AzureBlobStorageWriteSettings"
								}
							},
							"enableStaging": false
						},
						"inputs": [
							{
								"referenceName": "Binary2",
								"type": "DatasetReference",
								"parameters": {}
							}
						],
						"outputs": [
							{
								"referenceName": "Binary3",
								"type": "DatasetReference",
								"parameters": {}
							}
						]
					}
				],
				"policy": {
					"elapsedTimeMetric": {}
				},
				"parameters": {
					"p1": {
						"type": "string"
					},
					"p2": {
						"type": "string"
					}
				},
				"folder": {
					"name": "ADFTest"
				},
				"annotations": [],
				"lastPublishTime": "2022-07-26T05:44:25Z"
			},
			"dependsOn": []
		},
		{
			"name": "[concat(parameters('factoryName'), '/Rest_Copy')]",
			"type": "Microsoft.DataFactory/factories/pipelines",
			"apiVersion": "2018-06-01",
			"properties": {
				"activities": [
					{
						"name": "Rest_Copy",
						"type": "Copy",
						"dependsOn": [],
						"policy": {
							"timeout": "7.00:00:00",
							"retry": 0,
							"retryIntervalInSeconds": 30,
							"secureOutput": false,
							"secureInput": false
						},
						"userProperties": [],
						"typeProperties": {
							"source": {
								"type": "BinarySource",
								"storeSettings": {
									"type": "AzureBlobStorageReadSettings",
									"recursive": true
								},
								"formatSettings": {
									"type": "BinaryReadSettings"
								}
							},
							"sink": {
								"type": "BinarySink",
								"storeSettings": {
									"type": "AzureBlobStorageWriteSettings"
								}
							},
							"enableStaging": false
						},
						"inputs": [
							{
								"referenceName": "7zip",
								"type": "DatasetReference",
								"parameters": {}
							}
						],
						"outputs": [
							{
								"referenceName": "7zip",
								"type": "DatasetReference",
								"parameters": {}
							}
						]
					}
				],
				"policy": {
					"elapsedTimeMetric": {}
				},
				"folder": {
					"name": "ADFTest"
				},
				"annotations": [],
				"lastPublishTime": "2022-07-26T05:43:15Z"
			},
			"dependsOn": []
		},
		{
			"name": "[concat(parameters('factoryName'), '/SuspendTest01')]",
			"type": "Microsoft.DataFactory/factories/pipelines",
			"apiVersion": "2018-06-01",
			"properties": {
				"activities": [
					{
						"name": "Copy data1",
						"type": "Copy",
						"dependsOn": [
							{
								"activity": "Wait1",
								"dependencyConditions": [
									"Succeeded"
								]
							}
						],
						"policy": {
							"timeout": "7.00:00:00",
							"retry": 0,
							"retryIntervalInSeconds": 30,
							"secureOutput": false,
							"secureInput": false
						},
						"userProperties": [],
						"typeProperties": {
							"source": {
								"type": "BinarySource",
								"storeSettings": {
									"type": "AzureBlobStorageReadSettings",
									"recursive": true
								},
								"formatSettings": {
									"type": "BinaryReadSettings"
								}
							},
							"sink": {
								"type": "BinarySink",
								"storeSettings": {
									"type": "AzureBlobFSWriteSettings"
								}
							},
							"enableStaging": false
						},
						"inputs": [
							{
								"referenceName": "7zip",
								"type": "DatasetReference",
								"parameters": {}
							}
						],
						"outputs": [
							{
								"referenceName": "7zip_ADLSGen2",
								"type": "DatasetReference",
								"parameters": {}
							}
						]
					},
					{
						"name": "Wait1",
						"type": "Wait",
						"dependsOn": [],
						"userProperties": [],
						"typeProperties": {
							"waitTimeInSeconds": 120
						}
					},
					{
						"name": "Wait2",
						"type": "Wait",
						"dependsOn": [
							{
								"activity": "Copy data1",
								"dependencyConditions": [
									"Succeeded"
								]
							}
						],
						"userProperties": [],
						"typeProperties": {
							"waitTimeInSeconds": 120
						}
					},
					{
						"name": "Copy data2",
						"type": "Copy",
						"dependsOn": [
							{
								"activity": "Wait2",
								"dependencyConditions": [
									"Succeeded"
								]
							}
						],
						"policy": {
							"timeout": "7.00:00:00",
							"retry": 0,
							"retryIntervalInSeconds": 30,
							"secureOutput": false,
							"secureInput": false
						},
						"userProperties": [],
						"typeProperties": {
							"source": {
								"type": "BinarySource",
								"storeSettings": {
									"type": "AzureBlobStorageReadSettings",
									"recursive": true
								},
								"formatSettings": {
									"type": "BinaryReadSettings"
								}
							},
							"sink": {
								"type": "BinarySink",
								"storeSettings": {
									"type": "AzureBlobFSWriteSettings"
								}
							},
							"enableStaging": false
						},
						"inputs": [
							{
								"referenceName": "7zip",
								"type": "DatasetReference",
								"parameters": {}
							}
						],
						"outputs": [
							{
								"referenceName": "7zip_ADLSGen2",
								"type": "DatasetReference",
								"parameters": {}
							}
						]
					}
				],
				"policy": {
					"elapsedTimeMetric": {}
				},
				"annotations": [],
				"lastPublishTime": "2022-07-27T07:01:23Z"
			},
			"dependsOn": []
		},
		{
			"name": "[concat(parameters('factoryName'), '/pipeline1')]",
			"type": "Microsoft.DataFactory/factories/pipelines",
			"apiVersion": "2018-06-01",
			"properties": {
				"activities": [
					{
						"name": "Copy data1",
						"type": "Copy",
						"dependsOn": [],
						"policy": {
							"timeout": "7.00:00:00",
							"retry": 0,
							"retryIntervalInSeconds": 30,
							"secureOutput": false,
							"secureInput": false
						},
						"userProperties": [],
						"typeProperties": {
							"source": {
								"type": "BinarySource",
								"storeSettings": {
									"type": "AzureBlobStorageReadSettings",
									"recursive": true
								},
								"formatSettings": {
									"type": "BinaryReadSettings"
								}
							},
							"sink": {
								"type": "BinarySink",
								"storeSettings": {
									"type": "AzureBlobFSWriteSettings"
								}
							},
							"enableStaging": false
						},
						"inputs": [
							{
								"referenceName": "7zip",
								"type": "DatasetReference",
								"parameters": {}
							}
						],
						"outputs": [
							{
								"referenceName": "7zip_ADLSGen2",
								"type": "DatasetReference",
								"parameters": {}
							}
						]
					}
				],
				"policy": {
					"elapsedTimeMetric": {}
				},
				"annotations": [],
				"lastPublishTime": "2022-07-26T06:26:59Z"
			},
			"dependsOn": []
		},
		{
			"name": "[concat(parameters('factoryName'), '/pipeline10')]",
			"type": "Microsoft.DataFactory/factories/pipelines",
			"apiVersion": "2018-06-01",
			"properties": {
				"activities": [
					{
						"name": "Copy data1",
						"type": "Copy",
						"dependsOn": [],
						"policy": {
							"timeout": "0.12:00:00",
							"retry": 0,
							"retryIntervalInSeconds": 30,
							"secureOutput": false,
							"secureInput": false
						},
						"userProperties": [],
						"typeProperties": {
							"source": {
								"type": "DelimitedTextSource",
								"storeSettings": {
									"type": "AzureBlobStorageReadSettings",
									"recursive": true,
									"enablePartitionDiscovery": false
								},
								"formatSettings": {
									"type": "DelimitedTextReadSettings"
								}
							},
							"sink": {
								"type": "DelimitedTextSink",
								"storeSettings": {
									"type": "AzureBlobStorageWriteSettings"
								},
								"formatSettings": {
									"type": "DelimitedTextWriteSettings",
									"quoteAllText": true,
									"fileExtension": ".csv"
								}
							},
							"enableStaging": false,
							"translator": {
								"type": "TabularTranslator",
								"mappings": [
									{
										"source": {
											"name": "id",
											"type": "Int32",
											"physicalType": "String"
										},
										"sink": {
											"name": "id",
											"type": "String",
											"physicalType": "String"
										}
									},
									{
										"source": {
											"name": "num",
											"type": "Int32",
											"physicalType": "String"
										},
										"sink": {
											"name": "num",
											"type": "String",
											"physicalType": "String"
										}
									},
									{
										"source": {
											"name": "decimal",
											"type": "Int32",
											"physicalType": "String"
										},
										"sink": {
											"name": "decimal",
											"type": "String",
											"physicalType": "String"
										}
									},
									{
										"source": {
											"name": "single",
											"type": "Single",
											"physicalType": "String"
										},
										"sink": {
											"name": "single",
											"type": "String",
											"physicalType": "String"
										}
									},
									{
										"source": {
											"name": "double",
											"type": "Double",
											"physicalType": "String"
										},
										"sink": {
											"name": "double",
											"type": "String",
											"physicalType": "String"
										}
									},
									{
										"source": {
											"name": "string",
											"type": "String",
											"physicalType": "String"
										},
										"sink": {
											"name": "string",
											"type": "String",
											"physicalType": "String"
										}
									}
								],
								"typeConversion": true,
								"typeConversionSettings": {
									"allowDataTruncation": true,
									"treatBooleanAsNumber": false
								}
							}
						},
						"inputs": [
							{
								"referenceName": "Blob_CSV_2210280060000080",
								"type": "DatasetReference",
								"parameters": {}
							}
						],
						"outputs": [
							{
								"referenceName": "Blob_CSV_2210280060000080_out",
								"type": "DatasetReference",
								"parameters": {}
							}
						]
					}
				],
				"policy": {
					"elapsedTimeMetric": {}
				},
				"annotations": [],
				"lastPublishTime": "2023-03-11T09:41:45Z"
			},
			"dependsOn": []
		},
		{
			"name": "[concat(parameters('factoryName'), '/pipeline2')]",
			"type": "Microsoft.DataFactory/factories/pipelines",
			"apiVersion": "2018-06-01",
			"properties": {
				"activities": [
					{
						"name": "Web1",
						"type": "WebActivity",
						"dependsOn": [],
						"policy": {
							"timeout": "7.00:00:00",
							"retry": 0,
							"retryIntervalInSeconds": 30,
							"secureOutput": false,
							"secureInput": false
						},
						"userProperties": [],
						"typeProperties": {
							"url": "http://lb.private.contoso.com",
							"connectVia": {
								"referenceName": "integrationRuntimeManagedVnet",
								"type": "IntegrationRuntimeReference"
							},
							"method": "GET",
							"headers": {}
						}
					},
					{
						"name": "Copy data",
						"type": "Copy",
						"dependsOn": [],
						"policy": {
							"timeout": "7.00:00:00",
							"retry": 0,
							"retryIntervalInSeconds": 30,
							"secureOutput": false,
							"secureInput": false
						},
						"userProperties": [],
						"typeProperties": {
							"source": {
								"type": "BinarySource",
								"storeSettings": {
									"type": "AzureBlobStorageReadSettings",
									"recursive": true
								},
								"formatSettings": {
									"type": "BinaryReadSettings"
								}
							},
							"sink": {
								"type": "BinarySink",
								"storeSettings": {
									"type": "AzureBlobFSWriteSettings"
								}
							},
							"enableStaging": false
						},
						"inputs": [
							{
								"referenceName": "7zip",
								"type": "DatasetReference",
								"parameters": {}
							}
						],
						"outputs": [
							{
								"referenceName": "7zip_ADLSGen2",
								"type": "DatasetReference",
								"parameters": {}
							}
						]
					}
				],
				"policy": {
					"elapsedTimeMetric": {}
				},
				"annotations": [],
				"lastPublishTime": "2022-07-26T06:26:59Z"
			},
			"dependsOn": []
		},
		{
			"name": "[concat(parameters('factoryName'), '/pipeline6')]",
			"type": "Microsoft.DataFactory/factories/pipelines",
			"apiVersion": "2018-06-01",
			"properties": {
				"activities": [
					{
						"name": "Machine Learning Execute Pipeline1",
						"type": "AzureMLExecutePipeline",
						"dependsOn": [],
						"policy": {
							"timeout": "0.12:00:00",
							"retry": 0,
							"retryIntervalInSeconds": 30,
							"secureOutput": false,
							"secureInput": false
						},
						"userProperties": [],
						"typeProperties": {
							"mlExecutionType": "pipeline",
							"mlPipelineId": "702c4a36-09f0-42b2-9426-86f083c80094"
						},
						"linkedServiceName": {
							"referenceName": "AzureMLService2",
							"type": "LinkedServiceReference"
						}
					},
					{
						"name": "Machine Learning Execute Pipeline2",
						"type": "AzureMLExecutePipeline",
						"dependsOn": [],
						"policy": {
							"timeout": "0.12:00:00",
							"retry": 0,
							"retryIntervalInSeconds": 30,
							"secureOutput": false,
							"secureInput": false
						},
						"userProperties": [],
						"typeProperties": {
							"mlExecutionType": "pipeline",
							"mlPipelineEndpointId": "26bc00fa-aef6-48f9-b7cc-bc4d1be75cdf",
							"version": "0"
						},
						"linkedServiceName": {
							"referenceName": "AzureMLService1",
							"type": "LinkedServiceReference"
						}
					}
				],
				"policy": {
					"elapsedTimeMetric": {}
				},
				"annotations": []
			},
			"dependsOn": []
		},
		{
			"name": "[concat(parameters('factoryName'), '/rerun-test')]",
			"type": "Microsoft.DataFactory/factories/pipelines",
			"apiVersion": "2018-06-01",
			"properties": {
				"activities": [
					{
						"name": "rerun-test",
						"type": "Copy",
						"dependsOn": [],
						"policy": {
							"timeout": "7.00:00:00",
							"retry": 2,
							"retryIntervalInSeconds": 60,
							"secureOutput": false,
							"secureInput": false
						},
						"userProperties": [],
						"typeProperties": {
							"source": {
								"type": "DelimitedTextSource",
								"storeSettings": {
									"type": "AzureBlobFSReadSettings",
									"recursive": true,
									"wildcardFolderPath": "in",
									"wildcardFileName": "*",
									"enablePartitionDiscovery": false
								},
								"formatSettings": {
									"type": "DelimitedTextReadSettings"
								}
							},
							"sink": {
								"type": "ParquetSink",
								"storeSettings": {
									"type": "AzureBlobFSWriteSettings"
								},
								"formatSettings": {
									"type": "ParquetWriteSettings"
								}
							},
							"enableStaging": false,
							"translator": {
								"type": "TabularTranslator",
								"typeConversion": true,
								"typeConversionSettings": {
									"allowDataTruncation": true,
									"treatBooleanAsNumber": false
								}
							}
						},
						"inputs": [
							{
								"referenceName": "rerun_test_in",
								"type": "DatasetReference",
								"parameters": {}
							}
						],
						"outputs": [
							{
								"referenceName": "rerun_test_out2",
								"type": "DatasetReference",
								"parameters": {}
							}
						]
					}
				],
				"policy": {
					"elapsedTimeMetric": {}
				},
				"folder": {
					"name": "ADFTest"
				},
				"annotations": [],
				"lastPublishTime": "2022-07-26T05:43:15Z"
			},
			"dependsOn": []
		},
		{
			"name": "[concat(parameters('factoryName'), '/2210270060001002_in')]",
			"type": "Microsoft.DataFactory/factories/datasets",
			"apiVersion": "2018-06-01",
			"properties": {
				"linkedServiceName": {
					"referenceName": "Blob_2210270060001002",
					"type": "LinkedServiceReference"
				},
				"annotations": [],
				"type": "DelimitedText",
				"typeProperties": {
					"location": {
						"type": "AzureBlobStorageLocation",
						"fileName": "2210260060000755001_001.csv",
						"container": "2210270060001002-in"
					},
					"columnDelimiter": ",",
					"escapeChar": "\\",
					"quoteChar": "\""
				},
				"schema": []
			},
			"dependsOn": []
		},
		{
			"name": "[concat(parameters('factoryName'), '/2210270060001002_out')]",
			"type": "Microsoft.DataFactory/factories/datasets",
			"apiVersion": "2018-06-01",
			"properties": {
				"linkedServiceName": {
					"referenceName": "Blob_2210270060001002",
					"type": "LinkedServiceReference"
				},
				"parameters": {
					"Folderpass": {
						"type": "string"
					}
				},
				"annotations": [],
				"type": "DelimitedText",
				"typeProperties": {
					"location": {
						"type": "AzureBlobStorageLocation",
						"fileName": "Troubleinfo_h2s.csv",
						"folderPath": {
							"value": "@dataset().Folderpass",
							"type": "Expression"
						},
						"container": "2210270060001002-out"
					},
					"columnDelimiter": ",",
					"escapeChar": "\\",
					"quoteChar": "\""
				},
				"schema": []
			},
			"dependsOn": []
		},
		{
			"name": "[concat(parameters('factoryName'), '/AzureSqlTable1')]",
			"type": "Microsoft.DataFactory/factories/datasets",
			"apiVersion": "2018-06-01",
			"properties": {
				"linkedServiceName": {
					"referenceName": "AzureSqlDatabase1",
					"type": "LinkedServiceReference"
				},
				"annotations": [],
				"type": "AzureSqlTable",
				"schema": [
					{
						"name": "ID",
						"type": "int",
						"precision": 10
					},
					{
						"name": "Name",
						"type": "varchar"
					},
					{
						"name": "Model",
						"type": "varchar"
					},
					{
						"name": "Length",
						"type": "int",
						"precision": 10
					}
				],
				"typeProperties": {
					"schema": "dbo",
					"table": "Cars"
				}
			},
			"dependsOn": []
		},
		{
			"name": "[concat(parameters('factoryName'), '/AzureSqlTable2')]",
			"type": "Microsoft.DataFactory/factories/datasets",
			"apiVersion": "2018-06-01",
			"properties": {
				"linkedServiceName": {
					"referenceName": "AzureSqlDatabase1",
					"type": "LinkedServiceReference"
				},
				"annotations": [],
				"type": "AzureSqlTable",
				"schema": [],
				"typeProperties": {
					"schema": "dbo",
					"table": "Books"
				}
			},
			"dependsOn": []
		},
		{
			"name": "[concat(parameters('factoryName'), '/AzureSqlTable3')]",
			"type": "Microsoft.DataFactory/factories/datasets",
			"apiVersion": "2018-06-01",
			"properties": {
				"linkedServiceName": {
					"referenceName": "AzureSqlDatabase1",
					"type": "LinkedServiceReference"
				},
				"annotations": [],
				"type": "AzureSqlTable",
				"schema": [],
				"typeProperties": {
					"schema": "dbo",
					"table": "userTest"
				}
			},
			"dependsOn": []
		},
		{
			"name": "[concat(parameters('factoryName'), '/AzureSynapseAnalyticsTable1')]",
			"type": "Microsoft.DataFactory/factories/datasets",
			"apiVersion": "2018-06-01",
			"properties": {
				"linkedServiceName": {
					"referenceName": "AzureSynapseAnalytics5",
					"type": "LinkedServiceReference"
				},
				"annotations": [],
				"type": "AzureSqlDWTable",
				"schema": [],
				"typeProperties": {
					"schema": "dbo",
					"table": "test20230117"
				}
			},
			"dependsOn": []
		},
		{
			"name": "[concat(parameters('factoryName'), '/Binary1')]",
			"type": "Microsoft.DataFactory/factories/datasets",
			"apiVersion": "2018-06-01",
			"properties": {
				"linkedServiceName": {
					"referenceName": "FileServer1",
					"type": "LinkedServiceReference"
				},
				"annotations": [],
				"type": "Binary",
				"typeProperties": {
					"location": {
						"type": "FileServerLocation"
					}
				}
			},
			"dependsOn": []
		},
		{
			"name": "[concat(parameters('factoryName'), '/DelimitedText5')]",
			"type": "Microsoft.DataFactory/factories/datasets",
			"apiVersion": "2018-06-01",
			"properties": {
				"linkedServiceName": {
					"referenceName": "AzureBlobStorage8",
					"type": "LinkedServiceReference"
				},
				"parameters": {
					"folder": {
						"type": "string"
					}
				},
				"annotations": [],
				"type": "DelimitedText",
				"typeProperties": {
					"location": {
						"type": "AzureBlobStorageLocation",
						"folderPath": {
							"value": "@dataset().folder",
							"type": "Expression"
						},
						"container": "2302160060001405"
					},
					"columnDelimiter": ",",
					"escapeChar": "\\",
					"quoteChar": "\""
				},
				"schema": []
			},
			"dependsOn": []
		}
	]
}